SRC/lab2.v
module sumador_restador(
    input [3:0] A,
    input [3:0] B,
    input Sel,
    output [3:0] Suma,
    output Co
);
    wire [3:0] B_mod;
    
    // XOR para controlar si se suma o se resta
    assign B_mod = B ^ {4{Sel}}; 

    // Instancia del sumador (o uso de operador +)
    // El acarreo de entrada (Cin) es la misma señal Sel
    assign {Co, Suma} = A + B_mod + Sel;

endmodule

SRC/lab2_tb.v
`include "lab2.v"
`timescale 1ns / 1ps

module sumador_restador_tb;

    // Entradas
    reg [3:0] A;
    reg [3:0] B;
    reg Sel;

    // Salidas
    wire [3:0] Suma;
    wire Co;

    // Variables enteras para los bucles
    integer i, j;

    // Instanciar el módulo principal
    sumador_restador uut (
        .A(A), 
        .B(B), 
        .Sel(Sel), 
        .Suma(Suma), 
        .Co(Co)
    );

    // -----------------------------------------------------------
    // Bloque para generar el archivo de ondas (.vcd)
    // -----------------------------------------------------------
    initial begin
        $dumpfile("simulacion_sumador.vcd");
        $dumpvars(-1, uut);
    end

    // -----------------------------------------------------------
    // Bloque de estímulos (Prueba Exhaustiva Mejorada)
    // -----------------------------------------------------------
    initial begin
        $display("===============================================================");
        $display(" Iniciando simulacion exhaustiva (Suma y Resta emparejadas) ");
        $display("===============================================================\n");

        // Bucle externo para recorrer todos los valores de A (0 a 15)
        for (i = 0; i < 16; i = i + 1) begin
            A = i[3:0];
            
            // Bucle interno para recorrer todos los valores de B (0 a 15)
            for (j = 0; j < 16; j = j + 1) begin
                B = j[3:0];
                
                // 1. Probamos la SUMA
                Sel = 0;
                #5; // Esperamos a que el circuito reaccione
                $display("A=%d (bin:%b) | B=%d (bin:%b) || [SUMA  Sel=0] -> Suma=%d, Co=%b", 
                         A, A, B, B, Suma, Co);
                
                // 2. Probamos la RESTA inmediatamente después
                Sel = 1;
                #5; // Esperamos a que el circuito reaccione
                $display("A=%d (bin:%b) | B=%d (bin:%b) || [RESTA Sel=1] -> Suma=%b, Co=%b", 
                         A, A, B, B, Suma, Co);
                
                // Separador visual pequeño para el siguiente par de números
                $display("- - - - - - - - - - - - - - - - - - - - - - - - - - - - - - - - -");
            end
        end

        // Finalizar simulación
        #10;
        $display("\nSimulacion exhaustiva terminada con exito.");
        $finish;
    end
      
endmodule

SRC/simulacion_sumador.vcd
$date
	Thu Mar 12 19:42:08 2026
$end
$version
	Icarus Verilog
$end
$timescale
	1ps
$end
$scope module sumador_restador_tb $end
$scope module uut $end
$var wire 4 ! A [3:0] $end
$var wire 4 " B [3:0] $end
$var wire 4 # B_mod [3:0] $end
$var wire 1 $ Sel $end
$var wire 4 % Suma [3:0] $end
$var wire 1 & Co $end
$upscope $end
$upscope $end
$enddefinitions $end
$comment Show the parameter values. $end
$dumpall
$end
#0
$dumpvars
0&
b0 %
0$
b0 #
b0 "
b0 !
$end
#5000
1&
b1111 #
b0 %
1$
#10000
b1 %
0&
b1 #
0$
b1 "
#15000
b1110 #
b1111 %
1$
#20000
b10 %
b10 #
0$
b10 "
#25000
b1101 #
b1110 %
1$
#30000
b11 %
b11 #
0$
b11 "
#35000
b1100 #
b1101 %
1$
#40000
b100 %
b100 #
0$
b100 "
#45000
b1011 #
b1100 %
1$
#50000
b101 %
b101 #
0$
b101 "
#55000
b1010 #
b1011 %
1$
#60000
b110 %
b110 #
0$
b110 "
#65000
b1001 #
b1010 %
1$
#70000
b111 %
b111 #
0$
b111 "
#75000
b1000 #
b1001 %
1$
#80000
b1000 %
0$
b1000 "
#85000
b111 #
b1000 %
1$
#90000
b1001 %
b1001 #
0$
b1001 "
#95000
b110 #
b111 %
1$
#100000
b1010 %
b1010 #
0$
b1010 "
#105000
b101 #
b110 %
1$
#110000
b1011 %
b1011 #
0$
b1011 "
#115000
b100 #
b101 %
1$
#120000
b1100 %
b1100 #
0$
b1100 "
#125000
b11 #
b100 %
1$
#130000
b1101 %
b1101 #
0$
b1101 "
#135000
b10 #
b11 %
1$
#140000
b1110 %
b1110 #
0$
b1110 "
#145000
b1 #
b10 %
1$
#150000
b1111 %
b1111 #
0$
b1111 "
#155000
b0 #
b1 %
0&
1$
#160000
0$
b0 "
b1 !
#165000
1&
b1111 #
b1 %
1$
#170000
0&
b10 %
b1 #
0$
b1 "
#175000
1&
b1110 #
b0 %
1$
#180000
b11 %
0&
b10 #
0$
b10 "
#185000
b1101 #
b1111 %
1$
#190000
b100 %
b11 #
0$
b11 "
#195000
b1100 #
b1110 %
1$
#200000
b101 %
b100 #
0$
b100 "
#205000
b1011 #
b1101 %
1$
#210000
b110 %
b101 #
0$
b101 "
#215000
b1010 #
b1100 %
1$
#220000
b111 %
b110 #
0$
b110 "
#225000
b1001 #
b1011 %
1$
#230000
b1000 %
b111 #
0$
b111 "
#235000
b1000 #
b1010 %
1$
#240000
b1001 %
0$
b1000 "
#245000
b111 #
b1001 %
1$
#250000
b1010 %
b1001 #
0$
b1001 "
#255000
b110 #
b1000 %
1$
#260000
b1011 %
b1010 #
0$
b1010 "
#265000
b101 #
b111 %
1$
#270000
b1100 %
b1011 #
0$
b1011 "
#275000
b100 #
b110 %
1$
#280000
b1101 %
b1100 #
0$
b1100 "
#285000
b11 #
b101 %
1$
#290000
b1110 %
b1101 #
0$
b1101 "
#295000
b10 #
b100 %
1$
#300000
b1111 %
b1110 #
0$
b1110 "
#305000
b1 #
b11 %
0&
1$
#310000
1&
b0 %
b1111 #
0$
b1111 "
#315000
0&
b0 #
b10 %
1$
#320000
0$
b0 "
b10 !
#325000
1&
b1111 #
b10 %
1$
#330000
0&
b11 %
b1 #
0$
b1 "
#335000
1&
b1110 #
b1 %
1$
#340000
0&
b100 %
b10 #
0$
b10 "
#345000
1&
b1101 #
b0 %
1$
#350000
b101 %
0&
b11 #
0$
b11 "
#355000
b1100 #
b1111 %
1$
#360000
b110 %
b100 #
0$
b100 "
#365000
b1011 #
b1110 %
1$
#370000
b111 %
b101 #
0$
b101 "
#375000
b1010 #
b1101 %
1$
#380000
b1000 %
b110 #
0$
b110 "
#385000
b1001 #
b1100 %
1$
#390000
b1001 %
b111 #
0$
b111 "
#395000
b1000 #
b1011 %
1$
#400000
b1010 %
0$
b1000 "
#405000
b111 #
b1010 %
1$
#410000
b1011 %
b1001 #
0$
b1001 "
#415000
b110 #
b1001 %
1$
#420000
b1100 %
b1010 #
0$
b1010 "
#425000
b101 #
b1000 %
1$
#430000
b1101 %
b1011 #
0$
b1011 "
#435000
b100 #
b111 %
1$
#440000
b1110 %
b1100 #
0$
b1100 "
#445000
b11 #
b110 %
1$
#450000
b1111 %
b1101 #
0$
b1101 "
#455000
b10 #
b101 %
0&
1$
#460000
1&
b0 %
b1110 #
0$
b1110 "
#465000
0&
b1 #
b100 %
1$
#470000
1&
b1 %
b1111 #
0$
b1111 "
#475000
0&
b0 #
b11 %
1$
#480000
0$
b0 "
b11 !
#485000
1&
b1111 #
b11 %
1$
#490000
0&
b100 %
b1 #
0$
b1 "
#495000
1&
b1110 #
b10 %
1$
#500000
0&
b101 %
b10 #
0$
b10 "
#505000
1&
b1101 #
b1 %
1$
#510000
0&
b110 %
b11 #
0$
b11 "
#515000
1&
b1100 #
b0 %
1$
#520000
b111 %
0&
b100 #
0$
b100 "
#525000
b1011 #
b1111 %
1$
#530000
b1000 %
b101 #
0$
b101 "
#535000
b1010 #
b1110 %
1$
#540000
b1001 %
b110 #
0$
b110 "
#545000
b1001 #
b1101 %
1$
#550000
b1010 %
b111 #
0$
b111 "
#555000
b1000 #
b1100 %
1$
#560000
b1011 %
0$
b1000 "
#565000
b111 #
b1011 %
1$
#570000
b1100 %
b1001 #
0$
b1001 "
#575000
b110 #
b1010 %
1$
#580000
b1101 %
b1010 #
0$
b1010 "
#585000
b101 #
b1001 %
1$
#590000
b1110 %
b1011 #
0$
b1011 "
#595000
b100 #
b1000 %
1$
#600000
b1111 %
b1100 #
0$
b1100 "
#605000
b11 #
b111 %
0&
1$
#610000
1&
b0 %
b1101 #
0$
b1101 "
#615000
0&
b10 #
b110 %
1$
#620000
1&
b1 %
b1110 #
0$
b1110 "
#625000
0&
b1 #
b101 %
1$
#630000
1&
b10 %
b1111 #
0$
b1111 "
#635000
0&
b0 #
b100 %
1$
#640000
0$
b0 "
b100 !
#645000
1&
b1111 #
b100 %
1$
#650000
0&
b101 %
b1 #
0$
b1 "
#655000
1&
b1110 #
b11 %
1$
#660000
0&
b110 %
b10 #
0$
b10 "
#665000
1&
b1101 #
b10 %
1$
#670000
0&
b111 %
b11 #
0$
b11 "
#675000
1&
b1100 #
b1 %
1$
#680000
0&
b1000 %
b100 #
0$
b100 "
#685000
1&
b1011 #
b0 %
1$
#690000
b1001 %
0&
b101 #
0$
b101 "
#695000
b1010 #
b1111 %
1$
#700000
b1010 %
b110 #
0$
b110 "
#705000
b1001 #
b1110 %
1$
#710000
b1011 %
b111 #
0$
b111 "
#715000
b1000 #
b1101 %
1$
#720000
b1100 %
0$
b1000 "
#725000
b111 #
b1100 %
1$
#730000
b1101 %
b1001 #
0$
b1001 "
#735000
b110 #
b1011 %
1$
#740000
b1110 %
b1010 #
0$
b1010 "
#745000
b101 #
b1010 %
1$
#750000
b1111 %
b1011 #
0$
b1011 "
#755000
b100 #
b1001 %
0&
1$
#760000
1&
b0 %
b1100 #
0$
b1100 "
#765000
0&
b11 #
b1000 %
1$
#770000
1&
b1 %
b1101 #
0$
b1101 "
#775000
0&
b10 #
b111 %
1$
#780000
1&
b10 %
b1110 #
0$
b1110 "
#785000
0&
b1 #
b110 %
1$
#790000
1&
b11 %
b1111 #
0$
b1111 "
#795000
0&
b0 #
b101 %
1$
#800000
0$
b0 "
b101 !
#805000
1&
b1111 #
b101 %
1$
#810000
0&
b110 %
b1 #
0$
b1 "
#815000
1&
b1110 #
b100 %
1$
#820000
0&
b111 %
b10 #
0$
b10 "
#825000
1&
b1101 #
b11 %
1$
#830000
0&
b1000 %
b11 #
0$
b11 "
#835000
1&
b1100 #
b10 %
1$
#840000
0&
b1001 %
b100 #
0$
b100 "
#845000
1&
b1011 #
b1 %
1$
#850000
0&
b1010 %
b101 #
0$
b101 "
#855000
1&
b1010 #
b0 %
1$
#860000
b1011 %
0&
b110 #
0$
b110 "
#865000
b1001 #
b1111 %
1$
#870000
b1100 %
b111 #
0$
b111 "
#875000
b1000 #
b1110 %
1$
#880000
b1101 %
0$
b1000 "
#885000
b111 #
b1101 %
1$
#890000
b1110 %
b1001 #
0$
b1001 "
#895000
b110 #
b1100 %
1$
#900000
b1111 %
b1010 #
0$
b1010 "
#905000
b101 #
b1011 %
0&
1$
#910000
1&
b0 %
b1011 #
0$
b1011 "
#915000
0&
b100 #
b1010 %
1$
#920000
1&
b1 %
b1100 #
0$
b1100 "
#925000
0&
b11 #
b1001 %
1$
#930000
1&
b10 %
b1101 #
0$
b1101 "
#935000
0&
b10 #
b1000 %
1$
#940000
1&
b11 %
b1110 #
0$
b1110 "
#945000
0&
b1 #
b111 %
1$
#950000
1&
b100 %
b1111 #
0$
b1111 "
#955000
0&
b0 #
b110 %
1$
#960000
0$
b0 "
b110 !
#965000
1&
b1111 #
b110 %
1$
#970000
0&
b111 %
b1 #
0$
b1 "
#975000
1&
b1110 #
b101 %
1$
#980000
0&
b1000 %
b10 #
0$
b10 "
#985000
1&
b1101 #
b100 %
1$
#990000
0&
b1001 %
b11 #
0$
b11 "
#995000
1&
b1100 #
b11 %
1$
#1000000
0&
b1010 %
b100 #
0$
b100 "
#1005000
1&
b1011 #
b10 %
1$
#1010000
0&
b1011 %
b101 #
0$
b101 "
#1015000
1&
b1010 #
b1 %
1$
#1020000
0&
b1100 %
b110 #
0$
b110 "
#1025000
1&
b1001 #
b0 %
1$
#1030000
b1101 %
0&
b111 #
0$
b111 "
#1035000
b1000 #
b1111 %
1$
#1040000
b1110 %
0$
b1000 "
#1045000
b111 #
b1110 %
1$
#1050000
b1111 %
b1001 #
0$
b1001 "
#1055000
b110 #
b1101 %
0&
1$
#1060000
1&
b0 %
b1010 #
0$
b1010 "
#1065000
0&
b101 #
b1100 %
1$
#1070000
1&
b1 %
b1011 #
0$
b1011 "
#1075000
0&
b100 #
b1011 %
1$
#1080000
1&
b10 %
b1100 #
0$
b1100 "
#1085000
0&
b11 #
b1010 %
1$
#1090000
1&
b11 %
b1101 #
0$
b1101 "
#1095000
0&
b10 #
b1001 %
1$
#1100000
1&
b100 %
b1110 #
0$
b1110 "
#1105000
0&
b1 #
b1000 %
1$
#1110000
1&
b101 %
b1111 #
0$
b1111 "
#1115000
0&
b0 #
b111 %
1$
#1120000
0$
b0 "
b111 !
#1125000
1&
b1111 #
b111 %
1$
#1130000
0&
b1000 %
b1 #
0$
b1 "
#1135000
1&
b1110 #
b110 %
1$
#1140000
0&
b1001 %
b10 #
0$
b10 "
#1145000
1&
b1101 #
b101 %
1$
#1150000
0&
b1010 %
b11 #
0$
b11 "
#1155000
1&
b1100 #
b100 %
1$
#1160000
0&
b1011 %
b100 #
0$
b100 "
#1165000
1&
b1011 #
b11 %
1$
#1170000
0&
b1100 %
b101 #
0$
b101 "
#1175000
1&
b1010 #
b10 %
1$
#1180000
0&
b1101 %
b110 #
0$
b110 "
#1185000
1&
b1001 #
b1 %
1$
#1190000
0&
b1110 %
b111 #
0$
b111 "
#1195000
1&
b1000 #
b0 %
1$
#1200000
b1111 %
0&
0$
b1000 "
#1205000
b111 #
b1111 %
0&
1$
#1210000
1&
b0 %
b1001 #
0$
b1001 "
#1215000
0&
b110 #
b1110 %
1$
#1220000
1&
b1 %
b1010 #
0$
b1010 "
#1225000
0&
b101 #
b1101 %
1$
#1230000
1&
b10 %
b1011 #
0$
b1011 "
#1235000
0&
b100 #
b1100 %
1$
#1240000
1&
b11 %
b1100 #
0$
b1100 "
#1245000
0&
b11 #
b1011 %
1$
#1250000
1&
b100 %
b1101 #
0$
b1101 "
#1255000
0&
b10 #
b1010 %
1$
#1260000
1&
b101 %
b1110 #
0$
b1110 "
#1265000
0&
b1 #
b1001 %
1$
#1270000
1&
b110 %
b1111 #
0$
b1111 "
#1275000
0&
b0 #
b1000 %
1$
#1280000
0$
b0 "
b1000 !
#1285000
1&
b1111 #
b1000 %
1$
#1290000
0&
b1001 %
b1 #
0$
b1 "
#1295000
1&
b1110 #
b111 %
1$
#1300000
0&
b1010 %
b10 #
0$
b10 "
#1305000
1&
b1101 #
b110 %
1$
#1310000
0&
b1011 %
b11 #
0$
b11 "
#1315000
1&
b1100 #
b101 %
1$
#1320000
0&
b1100 %
b100 #
0$
b100 "
#1325000
1&
b1011 #
b100 %
1$
#1330000
0&
b1101 %
b101 #
0$
b101 "
#1335000
1&
b1010 #
b11 %
1$
#1340000
0&
b1110 %
b110 #
0$
b110 "
#1345000
1&
b1001 #
b10 %
1$
#1350000
0&
b1111 %
b111 #
0$
b111 "
#1355000
b1000 #
b1 %
1&
1$
#1360000
b0 %
0$
b1000 "
#1365000
b111 #
b0 %
1$
#1370000
b1 %
b1001 #
0$
b1001 "
#1375000
0&
b110 #
b1111 %
1$
#1380000
1&
b10 %
b1010 #
0$
b1010 "
#1385000
0&
b101 #
b1110 %
1$
#1390000
1&
b11 %
b1011 #
0$
b1011 "
#1395000
0&
b100 #
b1101 %
1$
#1400000
1&
b100 %
b1100 #
0$
b1100 "
#1405000
0&
b11 #
b1100 %
1$
#1410000
1&
b101 %
b1101 #
0$
b1101 "
#1415000
0&
b10 #
b1011 %
1$
#1420000
1&
b110 %
b1110 #
0$
b1110 "
#1425000
0&
b1 #
b1010 %
1$
#1430000
1&
b111 %
b1111 #
0$
b1111 "
#1435000
0&
b0 #
b1001 %
1$
#1440000
0$
b0 "
b1001 !
#1445000
1&
b1111 #
b1001 %
1$
#1450000
0&
b1010 %
b1 #
0$
b1 "
#1455000
1&
b1110 #
b1000 %
1$
#1460000
0&
b1011 %
b10 #
0$
b10 "
#1465000
1&
b1101 #
b111 %
1$
#1470000
0&
b1100 %
b11 #
0$
b11 "
#1475000
1&
b1100 #
b110 %
1$
#1480000
0&
b1101 %
b100 #
0$
b100 "
#1485000
1&
b1011 #
b101 %
1$
#1490000
0&
b1110 %
b101 #
0$
b101 "
#1495000
1&
b1010 #
b100 %
1$
#1500000
0&
b1111 %
b110 #
0$
b110 "
#1505000
b1001 #
b11 %
1&
1$
#1510000
b0 %
b111 #
0$
b111 "
#1515000
b1000 #
b10 %
1$
#1520000
b1 %
0$
b1000 "
#1525000
b111 #
b1 %
1$
#1530000
b10 %
b1001 #
0$
b1001 "
#1535000
b110 #
b0 %
1$
#1540000
b11 %
b1010 #
0$
b1010 "
#1545000
0&
b101 #
b1111 %
1$
#1550000
1&
b100 %
b1011 #
0$
b1011 "
#1555000
0&
b100 #
b1110 %
1$
#1560000
1&
b101 %
b1100 #
0$
b1100 "
#1565000
0&
b11 #
b1101 %
1$
#1570000
1&
b110 %
b1101 #
0$
b1101 "
#1575000
0&
b10 #
b1100 %
1$
#1580000
1&
b111 %
b1110 #
0$
b1110 "
#1585000
0&
b1 #
b1011 %
1$
#1590000
1&
b1000 %
b1111 #
0$
b1111 "
#1595000
0&
b0 #
b1010 %
1$
#1600000
0$
b0 "
b1010 !
#1605000
1&
b1111 #
b1010 %
1$
#1610000
0&
b1011 %
b1 #
0$
b1 "
#1615000
1&
b1110 #
b1001 %
1$
#1620000
0&
b1100 %
b10 #
0$
b10 "
#1625000
1&
b1101 #
b1000 %
1$
#1630000
0&
b1101 %
b11 #
0$
b11 "
#1635000
1&
b1100 #
b111 %
1$
#1640000
0&
b1110 %
b100 #
0$
b100 "
#1645000
1&
b1011 #
b110 %
1$
#1650000
0&
b1111 %
b101 #
0$
b101 "
#1655000
b1010 #
b101 %
1&
1$
#1660000
b0 %
b110 #
0$
b110 "
#1665000
b1001 #
b100 %
1$
#1670000
b1 %
b111 #
0$
b111 "
#1675000
b1000 #
b11 %
1$
#1680000
b10 %
0$
b1000 "
#1685000
b111 #
b10 %
1$
#1690000
b11 %
b1001 #
0$
b1001 "
#1695000
b110 #
b1 %
1$
#1700000
b100 %
b1010 #
0$
b1010 "
#1705000
b101 #
b0 %
1$
#1710000
b101 %
b1011 #
0$
b1011 "
#1715000
0&
b100 #
b1111 %
1$
#1720000
1&
b110 %
b1100 #
0$
b1100 "
#1725000
0&
b11 #
b1110 %
1$
#1730000
1&
b111 %
b1101 #
0$
b1101 "
#1735000
0&
b10 #
b1101 %
1$
#1740000
1&
b1000 %
b1110 #
0$
b1110 "
#1745000
0&
b1 #
b1100 %
1$
#1750000
1&
b1001 %
b1111 #
0$
b1111 "
#1755000
0&
b0 #
b1011 %
1$
#1760000
0$
b0 "
b1011 !
#1765000
1&
b1111 #
b1011 %
1$
#1770000
0&
b1100 %
b1 #
0$
b1 "
#1775000
1&
b1110 #
b1010 %
1$
#1780000
0&
b1101 %
b10 #
0$
b10 "
#1785000
1&
b1101 #
b1001 %
1$
#1790000
0&
b1110 %
b11 #
0$
b11 "
#1795000
1&
b1100 #
b1000 %
1$
#1800000
0&
b1111 %
b100 #
0$
b100 "
#1805000
b1011 #
b111 %
1&
1$
#1810000
b0 %
b101 #
0$
b101 "
#1815000
b1010 #
b110 %
1$
#1820000
b1 %
b110 #
0$
b110 "
#1825000
b1001 #
b101 %
1$
#1830000
b10 %
b111 #
0$
b111 "
#1835000
b1000 #
b100 %
1$
#1840000
b11 %
0$
b1000 "
#1845000
b111 #
b11 %
1$
#1850000
b100 %
b1001 #
0$
b1001 "
#1855000
b110 #
b10 %
1$
#1860000
b101 %
b1010 #
0$
b1010 "
#1865000
b101 #
b1 %
1$
#1870000
b110 %
b1011 #
0$
b1011 "
#1875000
b100 #
b0 %
1$
#1880000
b111 %
b1100 #
0$
b1100 "
#1885000
0&
b11 #
b1111 %
1$
#1890000
1&
b1000 %
b1101 #
0$
b1101 "
#1895000
0&
b10 #
b1110 %
1$
#1900000
1&
b1001 %
b1110 #
0$
b1110 "
#1905000
0&
b1 #
b1101 %
1$
#1910000
1&
b1010 %
b1111 #
0$
b1111 "
#1915000
0&
b0 #
b1100 %
1$
#1920000
0$
b0 "
b1100 !
#1925000
1&
b1111 #
b1100 %
1$
#1930000
0&
b1101 %
b1 #
0$
b1 "
#1935000
1&
b1110 #
b1011 %
1$
#1940000
0&
b1110 %
b10 #
0$
b10 "
#1945000
1&
b1101 #
b1010 %
1$
#1950000
0&
b1111 %
b11 #
0$
b11 "
#1955000
b1100 #
b1001 %
1&
1$
#1960000
b0 %
b100 #
0$
b100 "
#1965000
b1011 #
b1000 %
1$
#1970000
b1 %
b101 #
0$
b101 "
#1975000
b1010 #
b111 %
1$
#1980000
b10 %
b110 #
0$
b110 "
#1985000
b1001 #
b110 %
1$
#1990000
b11 %
b111 #
0$
b111 "
#1995000
b1000 #
b101 %
1$
#2000000
b100 %
0$
b1000 "
#2005000
b111 #
b100 %
1$
#2010000
b101 %
b1001 #
0$
b1001 "
#2015000
b110 #
b11 %
1$
#2020000
b110 %
b1010 #
0$
b1010 "
#2025000
b101 #
b10 %
1$
#2030000
b111 %
b1011 #
0$
b1011 "
#2035000
b100 #
b1 %
1$
#2040000
b1000 %
b1100 #
0$
b1100 "
#2045000
b11 #
b0 %
1$
#2050000
b1001 %
b1101 #
0$
b1101 "
#2055000
0&
b10 #
b1111 %
1$
#2060000
1&
b1010 %
b1110 #
0$
b1110 "
#2065000
0&
b1 #
b1110 %
1$
#2070000
1&
b1011 %
b1111 #
0$
b1111 "
#2075000
0&
b0 #
b1101 %
1$
#2080000
0$
b0 "
b1101 !
#2085000
1&
b1111 #
b1101 %
1$
#2090000
0&
b1110 %
b1 #
0$
b1 "
#2095000
1&
b1110 #
b1100 %
1$
#2100000
0&
b1111 %
b10 #
0$
b10 "
#2105000
b1101 #
b1011 %
1&
1$
#2110000
b0 %
b11 #
0$
b11 "
#2115000
b1100 #
b1010 %
1$
#2120000
b1 %
b100 #
0$
b100 "
#2125000
b1011 #
b1001 %
1$
#2130000
b10 %
b101 #
0$
b101 "
#2135000
b1010 #
b1000 %
1$
#2140000
b11 %
b110 #
0$
b110 "
#2145000
b1001 #
b111 %
1$
#2150000
b100 %
b111 #
0$
b111 "
#2155000
b1000 #
b110 %
1$
#2160000
b101 %
0$
b1000 "
#2165000
b111 #
b101 %
1$
#2170000
b110 %
b1001 #
0$
b1001 "
#2175000
b110 #
b100 %
1$
#2180000
b111 %
b1010 #
0$
b1010 "
#2185000
b101 #
b11 %
1$
#2190000
b1000 %
b1011 #
0$
b1011 "
#2195000
b100 #
b10 %
1$
#2200000
b1001 %
b1100 #
0$
b1100 "
#2205000
b11 #
b1 %
1$
#2210000
b1010 %
b1101 #
0$
b1101 "
#2215000
b10 #
b0 %
1$
#2220000
b1011 %
b1110 #
0$
b1110 "
#2225000
0&
b1 #
b1111 %
1$
#2230000
1&
b1100 %
b1111 #
0$
b1111 "
#2235000
0&
b0 #
b1110 %
1$
#2240000
0$
b0 "
b1110 !
#2245000
1&
b1111 #
b1110 %
1$
#2250000
0&
b1111 %
b1 #
0$
b1 "
#2255000
b1110 #
b1101 %
1&
1$
#2260000
b0 %
b10 #
0$
b10 "
#2265000
b1101 #
b1100 %
1$
#2270000
b1 %
b11 #
0$
b11 "
#2275000
b1100 #
b1011 %
1$
#2280000
b10 %
b100 #
0$
b100 "
#2285000
b1011 #
b1010 %
1$
#2290000
b11 %
b101 #
0$
b101 "
#2295000
b1010 #
b1001 %
1$
#2300000
b100 %
b110 #
0$
b110 "
#2305000
b1001 #
b1000 %
1$
#2310000
b101 %
b111 #
0$
b111 "
#2315000
b1000 #
b111 %
1$
#2320000
b110 %
0$
b1000 "
#2325000
b111 #
b110 %
1$
#2330000
b111 %
b1001 #
0$
b1001 "
#2335000
b110 #
b101 %
1$
#2340000
b1000 %
b1010 #
0$
b1010 "
#2345000
b101 #
b100 %
1$
#2350000
b1001 %
b1011 #
0$
b1011 "
#2355000
b100 #
b11 %
1$
#2360000
b1010 %
b1100 #
0$
b1100 "
#2365000
b11 #
b10 %
1$
#2370000
b1011 %
b1101 #
0$
b1101 "
#2375000
b10 #
b1 %
1$
#2380000
b1100 %
b1110 #
0$
b1110 "
#2385000
b1 #
b0 %
1$
#2390000
b1101 %
b1111 #
0$
b1111 "
#2395000
0&
b0 #
b1111 %
1$
#2400000
0$
b0 "
b1111 !
#2405000
b1111 #
b1111 %
1&
1$
#2410000
b0 %
b1 #
0$
b1 "
#2415000
b1110 #
b1110 %
1$
#2420000
b1 %
b10 #
0$
b10 "
#2425000
b1101 #
b1101 %
1$
#2430000
b10 %
b11 #
0$
b11 "
#2435000
b1100 #
b1100 %
1$
#2440000
b11 %
b100 #
0$
b100 "
#2445000
b1011 #
b1011 %
1$
#2450000
b100 %
b101 #
0$
b101 "
#2455000
b1010 #
b1010 %
1$
#2460000
b101 %
b110 #
0$
b110 "
#2465000
b1001 #
b1001 %
1$
#2470000
b110 %
b111 #
0$
b111 "
#2475000
b1000 #
b1000 %
1$
#2480000
b111 %
0$
b1000 "
#2485000
b111 #
b111 %
1$
#2490000
b1000 %
b1001 #
0$
b1001 "
#2495000
b110 #
b110 %
1$
#2500000
b1001 %
b1010 #
0$
b1010 "
#2505000
b101 #
b101 %
1$
#2510000
b1010 %
b1011 #
0$
b1011 "
#2515000
b100 #
b100 %
1$
#2520000
b1011 %
b1100 #
0$
b1100 "
#2525000
b11 #
b11 %
1$
#2530000
b1100 %
b1101 #
0$
b1101 "
#2535000
b10 #
b10 %
1$
#2540000
b1101 %
b1110 #
0$
b1110 "
#2545000
b1 #
b1 %
1$
#2550000
b1110 %
b1111 #
0$
b1111 "
#2555000
b0 #
b0 %
1$
